Workbook

Sheet Dashboard
B1: Personal Budget Dashboard
B3: INCOME ASSUMPTIONS | H3: SAVINGS GOALS TRACKER
B4: Annual Gross Salary | C4: 78000 | H4: Savings Bucket | I4: Target | J4: Saved So Far | K4: % Progress | L4: Months to Goal
B5: Pay Frequency (periods/yr) | C5: 26 | H5: House Down Payment | I5: 60000 | J5: 5000 | K5: =IF(I5=0,0,J5/I5) | L5: =IF(C23=0,"N/A",IF(J5>=I5,"Done",(I5-J5)/C23))
B6: Savings per Paycheck | C6: 700 | H6: Car Fund | I6: 15000 | J6: 2000 | K6: =IF(I6=0,0,J6/I6) | L6: =IF(C24=0,"N/A",IF(J6>=I6,"Done",(I6-J6)/C24))
B7: Tulsa Remote Grant (annual) | C7: 10000 | H7: Travel Fund | I7: 5000 | J7: 800 | K7: =IF(I7=0,0,J7/I7) | L7: =IF(C25=0,"N/A",IF(J7>=I7,"Done",(I7-J7)/C25))
B8: OK State Tax Rate | C8: 0.0475 | H8: Emergency Fund | I8: 10000 | J8: 3000 | K8: =IF(I8=0,0,J8/I8) | L8: =IF(C26=0,"N/A",IF(J8>=I8,"Done",(I8-J8)/C26))
B9: Federal Effective Tax Rate | C9: 0.18 | H9: General Savings | I9: 5000 | J9: 500 | K9: =IF(I9=0,0,J9/I9) | L9: =IF(C27=0,"N/A",IF(J9>=I9,"Done",(I9-J9)/C27))
B11: INCOME SUMMARY (MONTHLY)
B12: Gross Monthly Income | C12: =C4/12
B13: Federal Tax | C13: =-(C4*C9)/12
B14: State Tax | C14: =-(C4*C8)/12
B15: Total Deductions | C15: =C13+C14
B16: Net Monthly Take-Home | C16: =C12+C15
B17: Tulsa Remote Grant (monthly) | C17: =C7/12
B18: Net + Grant | C18: =C16+C17
B21: MONTHLY SAVINGS ALLOCATION
B22: Category | C22: Monthly | D22: Annual | E22: % of Income
B23: House Down Payment | C23: 1200 | D23: =C23*12 | E23: =C23/C16
B24: Car Fund | C24: 150 | D24: =C24*12 | E24: =C24/C16
B25: Travel Fund | C25: 200 | D25: =C25*12 | E25: =C25/C16
B26: Emergency Fund | C26: 300 | D26: =C26*12 | E26: =C26/C16
B27: General Savings | C27: 100 | D27: =C27*12 | E27: =C27/C16
B28: TOTAL SAVINGS | C28: =SUM(C23:C27) | D28: =SUM(D23:D27) | E28: =C28/C16
B30: REMAINING FOR LIVING EXPENSES | C30: =C18-C28

Sheet Monthly Budget
B1: Monthly Budget
B3: Month: | C3: January
B5: Category | C5: Budgeted | D5: Actual | E5: Difference | F5: % Used
B6: HOUSING & UTILITIES
B7: Rent / Mortgage | C7: 900 | D7: 0 | E7: =C7-D7 | F7: =IF(C7=0,0,D7/C7)
B8: Electric | C8: 80 | D8: 0 | E8: =C8-D8 | F8: =IF(C8=0,0,D8/C8)
B9: Water / Trash | C9: 40 | D9: 0 | E9: =C9-D9 | F9: =IF(C9=0,0,D9/C9)
B10: Internet | C10: 60 | D10: 0 | E10: =C10-D10 | F10: =IF(C10=0,0,D10/C10)
B11: Renter's Insurance | C11: 15 | D11: 0 | E11: =C11-D11 | F11: =IF(C11=0,0,D11/C11)
B13: FOOD
B14: Groceries | C14: 300 | D14: 0 | E14: =C14-D14 | F14: =IF(C14=0,0,D14/C14)
B15: Dining Out | C15: 100 | D15: 0 | E15: =C15-D15 | F15: =IF(C15=0,0,D15/C15)
B16: Coffee / Snacks | C16: 30 | D16: 0 | E16: =C16-D16 | F16: =IF(C16=0,0,D16/C16)
B18: TRANSPORTATION
B19: Gas | C19: 80 | D19: 0 | E19: =C19-D19 | F19: =IF(C19=0,0,D19/C19)
B20: Car Insurance | C20: 120 | D20: 0 | E20: =C20-D20 | F20: =IF(C20=0,0,D20/C20)
B21: Car Maintenance | C21: 50 | D21: 0 | E21: =C21-D21 | F21: =IF(C21=0,0,D21/C21)
B22: Parking / Tolls | C22: 15 | D22: 0 | E22: =C22-D22 | F22: =IF(C22=0,0,D22/C22)
B24: SUBSCRIPTIONS & TECH
B25: Phone Plan | C25: 50 | D25: 0 | E25: =C25-D25 | F25: =IF(C25=0,0,D25/C25)
B26: Streaming Services | C26: 30 | D26: 0 | E26: =C26-D26 | F26: =IF(C26=0,0,D26/C26)
B27: Software / Apps | C27: 15 | D27: 0 | E27: =C27-D27 | F27: =IF(C27=0,0,D27/C27)
B28: Cloud Storage | C28: 5 | D28: 0 | E28: =C28-D28 | F28: =IF(C28=0,0,D28/C28)
B30: PERSONAL CARE
B31: Health Insurance (if any) | C31: 0 | D31: 0 | E31: =C31-D31 | F31: =IF(C31=0,0,D31/C31)
B32: Gym / Fitness | C32: 35 | D32: 0 | E32: =C32-D32 | F32: =IF(C32=0,0,D32/C32)
B33: Haircuts / Grooming | C33: 25 | D33: 0 | E33: =C33-D33 | F33: =IF(C33=0,0,D33/C33)
B34: Medical / Dental | C34: 30 | D34: 0 | E34: =C34-D34 | F34: =IF(C34=0,0,D34/C34)
B36: ENTERTAINMENT & FUN
B37: Activities / Events | C37: 50 | D37: 0 | E37: =C37-D37 | F37: =IF(C37=0,0,D37/C37)
B38: Hobbies | C38: 30 | D38: 0 | E38: =C38-D38 | F38: =IF(C38=0,0,D38/C38)
B39: Gifts | C39: 25 | D39: 0 | E39: =C39-D39 | F39: =IF(C39=0,0,D39/C39)
B41: TRAVEL
B42: Travel Fund Spending | C42: 0 | D42: 0 | E42: =C42-D42 | F42: =IF(C42=0,0,D42/C42)
B44: TOTALS
B45: GRAND TOTAL | C45: =SUM(C7:C42) | D45: =SUM(D7:D42) | E45: =C45-D45 | F45: =IF(C45=0,0,D45/C45)
B46: NET MONTHLY INCOME (from Dashboard) | C46: ='Dashboard'!C18
B47: REMAINING AFTER EXPENSES | C47: =C46-D45

Sheet Annual Plan
B1: 12-Month Savings Projection
B3: MONTHLY SAVINGS PROJECTION
B4: Savings Bucket | C4: Jul | D4: Aug | E4: Sep | F4: Oct | G4: Nov | H4: Dec | I4: Jan | J4: Feb | K4: Mar | L4: Apr | M4: May | N4: Jun
B5: House Down Payment | C5: ='Dashboard'!C23 | D5: ='Dashboard'!C23 | E5: ='Dashboard'!C23 | F5: ='Dashboard'!C23 | G5: ='Dashboard'!C23 | H5: ='Dashboard'!C23 | I5: ='Dashboard'!C23 | J5: ='Dashboard'!C23 | K5: ='Dashboard'!C23 | L5: ='Dashboard'!C23 | M5: ='Dashboard'!C23 | N5: ='Dashboard'!C23
B6: Car Fund | C6: ='Dashboard'!C24 | D6: ='Dashboard'!C24 | E6: ='Dashboard'!C24 | F6: ='Dashboard'!C24 | G6: ='Dashboard'!C24 | H6: ='Dashboard'!C24 | I6: ='Dashboard'!C24 | J6: ='Dashboard'!C24 | K6: ='Dashboard'!C24 | L6: ='Dashboard'!C24 | M6: ='Dashboard'!C24 | N6: ='Dashboard'!C24
B7: Travel Fund | C7: ='Dashboard'!C25 | D7: ='Dashboard'!C25 | E7: ='Dashboard'!C25 | F7: ='Dashboard'!C25 | G7: ='Dashboard'!C25 | H7: ='Dashboard'!C25 | I7: ='Dashboard'!C25 | J7: ='Dashboard'!C25 | K7: ='Dashboard'!C25 | L7: ='Dashboard'!C25 | M7: ='Dashboard'!C25 | N7: ='Dashboard'!C25
B8: Emergency Fund | C8: ='Dashboard'!C26 | D8: ='Dashboard'!C26 | E8: ='Dashboard'!C26 | F8: ='Dashboard'!C26 | G8: ='Dashboard'!C26 | H8: ='Dashboard'!C26 | I8: ='Dashboard'!C26 | J8: ='Dashboard'!C26 | K8: ='Dashboard'!C26 | L8: ='Dashboard'!C26 | M8: ='Dashboard'!C26 | N8: ='Dashboard'!C26
B9: General Savings | C9: ='Dashboard'!C27 | D9: ='Dashboard'!C27 | E9: ='Dashboard'!C27 | F9: ='Dashboard'!C27 | G9: ='Dashboard'!C27 | H9: ='Dashboard'!C27 | I9: ='Dashboard'!C27 | J9: ='Dashboard'!C27 | K9: ='Dashboard'!C27 | L9: ='Dashboard'!C27 | M9: ='Dashboard'!C27 | N9: ='Dashboard'!C27
B10: Monthly Total | C10: =SUM(C5:C9) | D10: =SUM(D5:D9) | E10: =SUM(E5:E9) | F10: =SUM(F5:F9) | G10: =SUM(G5:G9) | H10: =SUM(H5:H9) | I10: =SUM(I5:I9) | J10: =SUM(J5:J9) | ... N10: =SUM(N5:N9)
B11: Cumulative Total | C11: =C10 | D11: =C11+D10 | E11: =D11+E10 | F11: =E11+F10 | G11: =F11+G10 | H11: =G11+H10 | I11: =H11+I10 | J11: =I11+J10 | K11: =J11+K10 | ... N11: =M11+N10
B13: TULSA REMOTE GRANT ALLOCATION
B14: Grant Applied to Rent | C14: ='Dashboard'!C7/12 | D14: ='Dashboard'!C7/12 | E14: ='Dashboard'!C7/12 | F14: ='Dashboard'!C7/12 | G14: ='Dashboard'!C7/12 | H14: ='Dashboard'!C7/12 | I14: ='Dashboard'!C7/12 | J14: ='Dashboard'!C7/12 | K14: ='Dashboard'!C7/12 | L14: ='Dashboard'!C7/12 | M14: ='Dashboard'!C7/12 | N14: ='Dashboard'!C7/12

Sheet City Comparison
B1: City Cost-of-Living Comparison
B3: COST COMPARISON
B4: Category | C4: Dallas | D4: Tulsa | E4: NW Arkansas | F4: Best Option
B5: Rent (1BR) | C5: 1200 | D5: 900 | E5: 950 | F5: =IF(AND(C5<=D5,C5<=E5),"Dallas",IF(AND(D5<=C5,D5<=E5),"Tulsa","NW Arkansas"))
B6: Grant Offset | C6: 0 | D6: -833 | E6: 0 | F6: =IF(AND(C6<=D6,C6<=E6),"Dallas",IF(AND(D6<=C6,D6<=E6),"Tulsa","NW Arkansas"))
B7: Effective Rent | C7: =C5+C6 | D7: =D5+D6 | E7: =E5+E6 | F7: =IF(AND(C7<=D7,C7<=E7),"Dallas",IF(AND(D7<=C7,D7<=E7),"Tulsa","NW Arkansas"))
B8: Utilities | C8: 150 | D8: 120 | E8: 125 | F8: =IF(AND(C8<=D8,C8<=E8),"Dallas",IF(AND(D8<=C8,D8<=E8),"Tulsa","NW Arkansas"))
B9: Groceries | C9: 350 | D9: 280 | E9: 290 | F9: =IF(AND(C9<=D9,C9<=E9),"Dallas",IF(AND(D9<=C9,D9<=E9),"Tulsa","NW Arkansas"))
B10: Gas (monthly) | C10: 100 | D10: 75 | E10: 80 | F10: =IF(AND(C10<=D10,C10<=E10),"Dallas",IF(AND(D10<=C10,D10<=E10),"Tulsa","NW Arkansas"))
B11: Car Insurance | C11: 140 | D11: 100 | E11: 110 | F11: =IF(AND(C11<=D11,C11<=E11),"Dallas",IF(AND(D11<=C11,D11<=E11),"Tulsa","NW Arkansas"))
B12: Dining Out | C12: 120 | D12: 80 | E12: 85 | F12: =IF(AND(C12<=D12,C12<=E12),"Dallas",IF(AND(D12<=C12,D12<=E12),"Tulsa","NW Arkansas"))
B13: State Tax Rate | C13: 0 | D13: 0.0475 | E13: 0.047 | F13: =IF(AND(C13<=D13,C13<=E13),"Dallas",IF(AND(D13<=C13,D13<=E13),"Tulsa","NW Arkansas"))
B14: Avg Home Price | C14: 350000 | D14: 210000 | E14: 240000 | F14: =IF(AND(C14<=D14,C14<=E14),"Dallas",IF(AND(D14<=C14,D14<=E14),"Tulsa","NW Arkansas"))

Sheet Net Worth Tracker
B1: Net Worth Tracker
B3: ASSETS
B4: Checking Account | C4: 2500
B5: Savings / HYSA | C5: 5000
B6: House Down Payment Fund | C6: 5000
B7: Car Fund | C7: 2000
B8: Travel Fund | C8: 800
B9: Emergency Fund | C9: 3000
B10: General Savings | C10: 500
B11: 401(k) | C11: 8000
B12: Investments / Brokerage | C12: 1500
B13: TOTAL ASSETS | C13: =SUM(C4:C12)
B15: LIABILITIES
B16: Car Loan | C16: 0
B17: Student Loans | C17: 0
B18: Credit Cards | C18: 0
B19: Other Debt | C19: 0
B20: TOTAL LIABILITIES | C20: =SUM(C16:C19)
B22: NET WORTH
B23: Total Net Worth | C23: =C13-C20
